README.rst
setup.py
test/test_hobeta.py
test/test_trdos.py
test/test_zeus2txt.py
zxtools/__init__.py
zxtools/hobeta.py
zxtools/trdos.py
zxtools/zeus2txt.py
zxtools.egg-info/PKG-INFO
zxtools.egg-info/SOURCES.txt
zxtools.egg-info/dependency_links.txt
zxtools.egg-info/entry_points.txt
zxtools.egg-info/requires.txt
zxtools.egg-info/top_level.txt