Metadata-Version: 1.1
Name: zxtools
Version: 1.0.22
Summary: Tools to manipulate files from ZX Spectrum
Home-page: http://www.codeatcpp.com
Author: Kirill V. Lyadvinsky
Author-email: mail@codeatcpp.com
License: BSD-3-Clause
Download-URL: https://github.com/codeatcpp/zxtools
Keywords: spectrum sinclair 48k z80 zeus zeus-asm
Platform: UNKNOWN
Classifier: Development Status :: 4 - Beta
Classifier: Operating System :: OS Independent
Classifier: Environment :: Console
Classifier: Intended Audience :: Developers
Classifier: License :: OSI Approved :: BSD License
Classifier: Programming Language :: Python :: 3
Classifier: Programming Language :: Python :: 3.2
Classifier: Programming Language :: Python :: 3.3
Classifier: Programming Language :: Python :: 3.4
Classifier: Programming Language :: Python :: 3.5
Classifier: Programming Language :: Python :: Implementation :: CPython
Classifier: Topic :: Software Development
Classifier: Topic :: Utilities
